{"apikey":true,"result":true,"Data":[{"_id":"5dab0ea32dd4f37f5c619828","cDate":"19-10-2019","cTime":"1:24 pm","timestamp":"1571491491694","catName":"Bengali","scat":"5","rdate":"21","rmonth":"06","ryear":"2019","sposter":"http://api.luckyboy.pw/api/img/mposter/6654600BibahoObhijaan(2019).jpg","thumbnail":"http://api.luckyboy.pw/api/img/mthumbnail/8277930BibahoObhijaan(2019)THUMB.jpg","title":"Bibaho Obhijaan (2019)","language":"Bengali","slanguage":"10","sgenre":"2","genreName":"Comedy","desc":"A comedy caper involving two childhood friends Anupam (Ankush) and Rajat (Rudranil Ghosh) who decide to get married. Soon after they realise the consequences of conjugal life. Thus starts their marital adventure or Bibaho Obhijaan, a roller-coaster laughter riot!","mduration":"2 hours 1 minutes","msize":"383 MB","mtrailksa360p":"null","mtrailksa480p":"null","mtrailksa720p":"http://dl3.luckyboy.pw/files/Bibaho_Obhijaan_(2019)_Bengali_480p_Original_HDRip_Full_Movie-(MovieMate).mkv","mtrailksa1080p":"null","fmdav360p":"0","fmdav480p":"1","fmdav720p":"0","fmdav1080p":"0","fmdsize360p":"N/A","fmdsize480p":"383.70 MB","fmdsize720p":"N/A","fmdsize1080p":"N/A","mactive":"1","uploadby":"undefined","umid":"779f629a-bcf1-407e-be5c-3615e7f22fff","likes":"13","downloads":"0"},{"_id":"5dab09ef3fd66d6fc84129cb","cDate":"19-10-2019","cTime":"1:04 pm","timestamp":"1571490287162","catName":"Bengali","scat":"5","rdate":"28","rmonth":"07","ryear":"2017","sposter":"http://api.luckyboy.pw/api/img/mposter/3210727Nabab.jpg","thumbnail":"http://api.luckyboy.pw/api/img/mthumbnail/7932980maxresdefault(1).jpg","title":"Nabab (2017)","language":"Bengali","slanguage":"10","sgenre":"14","genreName":"Thriller","desc":"An intelligence agent from Bangladesh tasked with a secret operation in West Bengal, India.","mduration":"2 hours 40 minutes ","msize":"505 MB","mtrailksa360p":"null","mtrailksa480p":"null","mtrailksa720p":"http://dl2.luckyboy.pw/files/Nabab_(2017)_Bengali_480p_Original_HDRip_Full_Bengali_Movie-(MovieMate).mkv","mtrailksa1080p":"null","fmdav360p":"0","fmdav480p":"1","fmdav720p":"0","fmdav1080p":"0","fmdsize360p":"N/A","fmdsize480p":"505.88 MB","fmdsize720p":"N/A","fmdsize1080p":"N/A","mactive":"1","uploadby":"undefined","umid":"3027e5be-ff7c-4579-9a3b-2e7bf232cd99","likes":"14","downloads":"0"},{"_id":"5d9c26b1755d037802c78b57","cDate":"08-10-2019","cTime":"6:03 am","timestamp":"1570514609629","catName":"Bengali","scat":"5","rdate":"26","rmonth":"07","ryear":"2019","sposter":"http://api.luckyboy.pw/api/img/mposter/2669962Bornoporichoy.jpg","thumbnail":"http://api.luckyboy.pw/api/img/mthumbnail/4131363BornoporichoyMOVIE.jpg","title":"Bornoporichoy: A Grammar Of Death (2019)","language":"Bengali","slanguage":"10","sgenre":"14","genreName":"Thriller","desc":"Dhananjoy, a police detective, is drawn back into the case that ruined his life and career at the request of his colleagues. Reluctant at first, he dives head first into the case to nab the...","mduration":"2 hours 2 minutes","msize":"322 MB","mtrailksa360p":"null","mtrailksa480p":"null","mtrailksa720p":"http://dl2.luckyboy.pw/files/Bornoporichoy_A_Grammar_Of_Death_(2019)_Bengali_Full_Movie-(MovieMate).mkv","mtrailksa1080p":"null","fmdav360p":"0","fmdav480p":"1","fmdav720p":"0","fmdav1080p":"0","fmdsize360p":"N/A","fmdsize480p":"322.99 MB","fmdsize720p":"N/A","fmdsize1080p":"N/A","mactive":"1","uploadby":"undefined","umid":"9bca34c4-7d0d-4719-b1b7-ba8b05f74002","likes":"14","downloads":"0"},{"_id":"5d9c25b52647846f1d421cb1","cDate":"08-10-2019","cTime":"5:59 am","timestamp":"1570514357596","catName":"Bengali","scat":"5","rdate":"01","rmonth":"10","ryear":"2019","sposter":"http://api.luckyboy.pw/api/img/mposter/2205391YuddhamSharanam2019.jpg","thumbnail":"http://api.luckyboy.pw/api/img/mthumbnail/146489YuddhamSharanam.jpg","title":"Yuddham Sharanam (2019)","language":"Bengali","slanguage":"10","sgenre":"1","genreName":"Action","desc":"A young man is inconsolable after his parents die under mysterious circumstances. However, he decides to go on a quest to find the real reason behind their deaths and to avenge them.","mduration":"2 hours 21 minutes","msize":"400 MB","mtrailksa360p":"null","mtrailksa480p":"null","mtrailksa720p":"http://dl2.luckyboy.pw/files/Yuddham_Sharanam_2019_Bengali_Dubbed_Full_Movie-(MovieMate).mkv","mtrailksa1080p":"null","fmdav360p":"0","fmdav480p":"1","fmdav720p":"0","fmdav1080p":"0","fmdsize360p":"N/A","fmdsize480p":"400.19 MB","fmdsize720p":"N/A","fmdsize1080p":"N/A","mactive":"1","uploadby":"undefined","umid":"1670efcc-d9e1-4bbb-b2cd-ea36a8b7c2bc","likes":"8","downloads":"0"},{"_id":"5d9c2410b545916ae0a5be10","cDate":"08-10-2019","cTime":"5:52 am","timestamp":"1570513936519","catName":"Bengali","scat":"5","rdate":"14","rmonth":"08","ryear":"2019","sposter":"http://api.luckyboy.pw/api/img/mposter/1234038SonOfSatyamurthy(2019).jpg","thumbnail":"http://api.luckyboy.pw/api/img/mthumbnail/7618677maxresdefault.jpg","title":"Son Of Satyamurthy (2019)","language":"Bengali","slanguage":"10","sgenre":"1","genreName":"Action","desc":"Anand, the son of a rich businessman, struggles to save his father's wealth after his demise. However, he faces many challenges when he becomes the sole breadwinner of his family.","mduration":"2 hours 52 minutes","msize":"442 MB","mtrailksa360p":"null","mtrailksa480p":"null","mtrailksa720p":"http://dl2.luckyboy.pw/files/Son_Of_Satyamurthy_(2019)_480p_Bengali_Dubbed_Full_Movie-(MovieMate).mkv","mtrailksa1080p":"null","fmdav360p":"0","fmdav480p":"1","fmdav720p":"0","fmdav1080p":"0","fmdsize360p":"N/A","fmdsize480p":"442.45 MB","fmdsize720p":"N/A","fmdsize1080p":"N/A","mactive":"1","uploadby":"undefined","umid":"1918cda5-dada-456f-a4c0-ac6811204ef3","likes":"7","downloads":"0"},{"_id":"5d9c22eb13f66e65e16b7a41","cDate":"08-10-2019","cTime":"5:47 am","timestamp":"1570513643548","catName":"Bengali","scat":"5","rdate":"21","rmonth":"09","ryear":"2019","sposter":"http://api.luckyboy.pw/api/img/mposter/5820740Charki(2019).jpg","thumbnail":"http://api.luckyboy.pw/api/img/mthumbnail/6849874Charki.png","title":"Charki (2019)","language":"Bengali","slanguage":"10","sgenre":"6","genreName":"Drama","desc":"Charki is Bengali film starring Biswanath Basu, Shantilal Mukherjee, Arunabha Dey and Oishika Guhathakurata. Story revolves around Charki, a young mischievous girl who lags in studies. Her life changes when a veteran teacher enters her life and uses unconventional ways of teaching.","mduration":"2 hours 15 minutes","msize":"434 MB","mtrailksa360p":"null","mtrailksa480p":"null","mtrailksa720p":"http://dl2.luckyboy.pw/files/Charki_(2019)_Bengali_Full_Movie_480p_HDRip-(MovieMate).mkv","mtrailksa1080p":"null","fmdav360p":"0","fmdav480p":"1","fmdav720p":"0","fmdav1080p":"0","fmdsize360p":"N/A","fmdsize480p":"434.16 MB","fmdsize720p":"N/A","fmdsize1080p":"N/A","mactive":"1","uploadby":"undefined","umid":"99424614-2c5b-4818-ab4e-41256b1e3e78","likes":"2","downloads":"0"},{"_id":"5d9c1a8631a594427e9c8fb9","cDate":"08-10-2019","cTime":"5:11 am","timestamp":"1570511494154","catName":"Bengali","scat":"5","rdate":"25","rmonth":"12","ryear":"2015","sposter":"http://api.luckyboy.pw/api/img/mposter/6331262Arshinagar(2015).jpg","thumbnail":"http://api.luckyboy.pw/api/img/mthumbnail/4423801Arshinagar(2015).webp","title":"Arshinagar (2015)","language":"Bengali","slanguage":"10","sgenre":"5","genreName":"Romance","desc":"Ranajit and Julekha belong to rival families where the enmity between them goes way back. However, when they meet, there is an unbeatable connection that eventually turns to love.","mduration":"2 hours 14 minutes ","msize":"579 MB","mtrailksa360p":"null","mtrailksa480p":"null","mtrailksa720p":"http://dl2.luckyboy.pw/files/Arshinagar_2015_Bengali_Full_Movie-(MovieMate).mkv","mtrailksa1080p":"null","fmdav360p":"0","fmdav480p":"1","fmdav720p":"0","fmdav1080p":"0","fmdsize360p":"N/A","fmdsize480p":"579.61 MB","fmdsize720p":"N/A","fmdsize1080p":"N/A","mactive":"1","uploadby":"undefined","umid":"08c277b0-384c-4d48-8793-fe1f08fbc929","likes":"8","downloads":"0"},{"_id":"5d9a44285ec2b94b91ca1649","cDate":"06-10-2019","cTime":"7:44 pm","timestamp":"1570391080505","catName":"Bengali","scat":"5","rdate":"11","rmonth":"07","ryear":"2010","sposter":"http://api.luckyboy.pw/api/img/mposter/1570205LeChakka.jpg","thumbnail":"http://api.luckyboy.pw/api/img/mthumbnail/7150858LeChakkaMOVIE.jpg","title":"Le Chakka (2010)","language":"Bengali","slanguage":"10","sgenre":"2","genreName":"Comedy","desc":"Abir visits his family in Dorjipara which is home to 11 bullets, a cricket team that is out of luck. Abir gives them their first match win ever and also sets their land free from a political goon.","mduration":"2 hours 8 minutes","msize":"366 MB","mtrailksa360p":"null","mtrailksa480p":"null","mtrailksa720p":"http://dl2.luckyboy.pw/files/Le_Chakka_2010_Bengali_Full_Movie_480p_HDTV-(MovieMate).mp4","mtrailksa1080p":"null","fmdav360p":"0","fmdav480p":"1","fmdav720p":"0","fmdav1080p":"0","fmdsize360p":"N/A","fmdsize480p":"366.67 MB","fmdsize720p":"N/A","fmdsize1080p":"N/A","mactive":"1","uploadby":"undefined","umid":"ca6b9524-f47c-4b95-afcc-d12ba45c4564","likes":"6","downloads":"0"},{"_id":"5d9a430215f0544973556bff","cDate":"06-10-2019","cTime":"7:39 pm","timestamp":"1570390786621","catName":"Bengali","scat":"5","rdate":"17","rmonth":"05","ryear":"2013","sposter":"http://api.luckyboy.pw/api/img/mposter/8258127MahapurushOKapurush.jpg","thumbnail":"http://api.luckyboy.pw/api/img/mthumbnail/7780317MahapurushOKapurushBENGALI.jpg","title":"Mahapurush O Kapurush","language":"Bengali","slanguage":"10","sgenre":"2","genreName":"Comedy","desc":"Two conmen, Swami Swadgajananda and Pada, make their living by fooling people. While Swami Swadgajananda claims to be an incarnation of God, Pada robs people's houses.","mduration":"2 hours 5 minutes","msize":"405 MB","mtrailksa360p":"null","mtrailksa480p":"null","mtrailksa720p":"http://dl2.luckyboy.pw/files/Mahapurush_O_Kapurush_2013_Bengali_Full_Movie-(MovieMate).mp4","mtrailksa1080p":"null","fmdav360p":"0","fmdav480p":"1","fmdav720p":"0","fmdav1080p":"0","fmdsize360p":"N/A","fmdsize480p":"405.29 MB","fmdsize720p":"N/A","fmdsize1080p":"N/A","mactive":"1","uploadby":"undefined","umid":"3b598f85-e6e9-4323-8001-afbea9c2a383","likes":"2","downloads":"0"},{"_id":"5d9a424e7b5b5d47f088c145","cDate":"06-10-2019","cTime":"7:36 pm","timestamp":"1570390606904","catName":"Bengali","scat":"5","rdate":"30","rmonth":"05","ryear":"2014","sposter":"http://api.luckyboy.pw/api/img/mposter/2176508Arundhati.jpg","thumbnail":"http://api.luckyboy.pw/api/img/mthumbnail/2911647Arundhatimovie.jpg","title":"Arundhati (2014)","language":"Bengali","slanguage":"10","sgenre":"11","genreName":"Fantasy","desc":"When Arundhati visits her native village, she learns that she looks exactly like her great-grandmother, Jejamma, a warrior princess, and she must defeat the evil forces to survive.","mduration":"2 hours 25 minutes","msize":"477 MB","mtrailksa360p":"null","mtrailksa480p":"null","mtrailksa720p":"http://dl2.luckyboy.pw/files/Arundhati_2014_Bengali_Movie_WEBHD_480p-(MovieMate).mp4","mtrailksa1080p":"null","fmdav360p":"0","fmdav480p":"1","fmdav720p":"0","fmdav1080p":"0","fmdsize360p":"N/A","fmdsize480p":"477.15 MB","fmdsize720p":"N/A","fmdsize1080p":"N/A","mactive":"1","uploadby":"undefined","umid":"2e6f47b2-f2fd-49ad-a073-348531bba2ec","likes":"10","downloads":"0"},{"_id":"5d9a412b5aea8445c805a2ab","cDate":"06-10-2019","cTime":"7:31 pm","timestamp":"1570390315794","catName":"Bengali","scat":"5","rdate":"07","rmonth":"11","ryear":"2014","sposter":"http://api.luckyboy.pw/api/img/mposter/74282069f6f7448b48e4420fc50b1451e5421ec.jpg","thumbnail":"http://api.luckyboy.pw/api/img/mthumbnail/2978093maxresdefault.jpg","title":"Khaad (2014)","language":"Bengali","slanguage":"10","sgenre":"9","genreName":"Adventure","desc":"A group of people meet with a terrible accident while venturing on a journey, but they miraculously survive. Deserted, these travellers end up playing a game and revealing their darkest secrets.","mduration":"2 hours 20 minutes","msize":"344 MB","mtrailksa360p":"null","mtrailksa480p":"null","mtrailksa720p":"http://dl2.luckyboy.pw/files/Khaad_2014_Bengali_Full_Movie_HDRip_480p-(MovieMate).mp4","mtrailksa1080p":"null","fmdav360p":"0","fmdav480p":"1","fmdav720p":"0","fmdav1080p":"0","fmdsize360p":"N/A","fmdsize480p":"344.02 MB","fmdsize720p":"N/A","fmdsize1080p":"N/A","mactive":"1","uploadby":"undefined","umid":"b2d6e50e-f794-4110-87e0-c541c8f4be76","likes":"4","downloads":"0"}]}